tiny_recipe/__init__.py
tiny_recipe/_modidx.py
tiny_recipe/actions.py
tiny_recipe/core.py
tiny_recipe-0.0.2.dist-info/LICENSE
tiny_recipe-0.0.2.dist-info/METADATA
tiny_recipe-0.0.2.dist-info/WHEEL
tiny_recipe-0.0.2.dist-info/entry_points.txt
tiny_recipe-0.0.2.dist-info/top_level.txt
tiny_recipe-0.0.2.dist-info/RECORD
